{"namedChunkGroups":{"polyfill":{"name":"polyfill","assets":[{"name":"webpack-runtime-9de1ab1b57224925be49.js","size":4966},{"name":"polyfill-917ce7c99d72bba574df.js","size":82633}],"filteredAssets":0,"assetsSize":87599,"filteredAuxiliaryAssets":2,"auxiliaryAssetsSize":221321},"app":{"name":"app","assets":[{"name":"webpack-runtime-9de1ab1b57224925be49.js","size":4966},{"name":"framework-3f8c44646e37d96d551e.js","size":129734},{"name":"app-85e0cadc1e71cf25e93c.js","size":111822}],"filteredAssets":0,"assetsSize":246522,"filteredAuxiliaryAssets":3,"auxiliaryAssetsSize":790164},"component---src-pages-404-js":{"name":"component---src-pages-404-js","assets":[{"name":"component---src-pages-404-js-379a5bfc8717aea2b411.js","size":808}],"filteredAssets":0,"assetsSize":808,"filteredAuxiliaryAssets":1,"auxiliaryAssetsSize":1884},"component---src-pages-index-js":{"name":"component---src-pages-index-js","assets":[{"name":"styles.04e4ece4fdd956d77c4e.css","size":1575},{"name":"component---src-pages-index-js-99b91490b7fdc2ebc6c8.js","size":69394}],"filteredAssets":0,"assetsSize":70969,"filteredAuxiliaryAssets":1,"auxiliaryAssetsSize":233324}},"assetsByChunkName":{"polyfill":["webpack-runtime-9de1ab1b57224925be49.js","polyfill-917ce7c99d72bba574df.js"],"app":["webpack-runtime-9de1ab1b57224925be49.js","framework-3f8c44646e37d96d551e.js","app-85e0cadc1e71cf25e93c.js"],"component---src-pages-404-js":["component---src-pages-404-js-379a5bfc8717aea2b411.js"],"component---src-pages-index-js":["styles.04e4ece4fdd956d77c4e.css","component---src-pages-index-js-99b91490b7fdc2ebc6c8.js"]},"childAssetsByChunkName":{}}